funJplot/__init__.py
funJplot/base.py
funJplot/matrix/__init__.py
funJplot/matrix/geometrics_transpose.py
funJplot/parametric_curves/__init__.py
funJplot/parametric_curves/base.py
funJplot/parametric_curves/curves.py
funJplot/parametric_curves/curves3d.py
funJplot/utils/data_retriving_tools.py
funJplot/utils/test.py
funjplot-0.0.0.6.dist-info/licenses/LICENSE
funjplot-0.0.0.6.dist-info/METADATA
funjplot-0.0.0.6.dist-info/WHEEL
funjplot-0.0.0.6.dist-info/top_level.txt
funjplot-0.0.0.6.dist-info/RECORD
