Metadata-Version: 2.4
Name: funJplot
Version: 0.0.0.6
Summary: A library for creating animated visualizations of mathematical curves and concepts using Plotly.
Author-email: Simone Pellacani <pellacanisimone2017@gmail.com>
License: MIT License
Project-URL: Homepage, https://github.com/pellacaniSimone/funJplot
Project-URL: Issues, https://github.com/pellacaniSimone/funJplot/issues
Keywords: plotly,animation,math,geometry,visualization,curves
Classifier: Programming Language :: Python :: 3
Classifier: License :: OSI Approved :: MIT License
Classifier: Operating System :: OS Independent
Classifier: Intended Audience :: Education
Classifier: Intended Audience :: Science/Research
Classifier: Topic :: Scientific/Engineering :: Visualization
Requires-Python: >=3.11
License-File: LICENSE
Requires-Dist: numpy>=2.0.0
Requires-Dist: plotly>=6.0.1
Requires-Dist: jupyterlab>=4.4.0
Dynamic: license-file
